{
  "date": "22/03/2026, 06:49:49",
  "data": [
    {
      "title": "Pulsioni",
      "type": "movie",
      "platform": "Amazon Prime Video",
      "releaseDate": "2026-03-01",
      "displayDate": "1 Marzo 2026",
      "description": "Un thriller avvincente.",
      "posterUrl": ""
    },
    {
      "title": "SpongeBob, il film",
      "type": "movie",
      "platform": "Amazon Prime Video",
      "releaseDate": "2026-03-01",
      "displayDate": "1 Marzo 2026",
      "description": "Film d'animazione basato sul popolare personaggio.",
      "posterUrl": "https://image.tmdb.org/t/p/w500/d4OEgVm2PEI63n83U58LerLUF07.jpg"
    },
    {
      "title": "Law & Order: Special Victims Unit Stagione 27",
      "type": "tv",
      "platform": "Sky (incl. NOW)",
      "releaseDate": "2026-03-01",
      "displayDate": "1 Marzo 2026",
      "description": "Ventisettesima stagione del legal drama.",
      "posterUrl": ""
    },
    {
      "title": "All Her Fault",
      "type": "tv",
      "platform": "Sky (incl. NOW)",
      "releaseDate": "2026-03-01",
      "displayDate": "1 Marzo 2026",
      "description": "Nuova serie thriller con Sarah Snook.",
      "posterUrl": "https://image.tmdb.org/t/p/w500/o8vZKZlc8H4OcgpbJuqP0iK4B2.jpg"
    },
    {
      "title": "Mio Fratello è un Vichingo - The Last Viking",
      "type": "movie",
      "platform": "Cinema in Italia",
      "releaseDate": "2026-03-01",
      "displayDate": "1 Marzo 2026",
      "description": "Film.",
      "posterUrl": "https://image.tmdb.org/t/p/w500/7U6sjWTdcpRbS6rfCyoffsN6igY.jpg"
    },
    {
      "title": "Breve sinossi non disponibile.",
      "type": "tv",
      "platform": "Discovery+",
      "releaseDate": "2026-03-01",
      "displayDate": "1 Marzo 2026",
      "description": "Nessun titolo confermato trovato per questo periodo.",
      "posterUrl": ""
    },
    {
      "title": "Demon Slayer: Kimetsu No Yaiba: Hashira Training Arc",
      "type": "tv",
      "platform": "Netflix",
      "releaseDate": "2026-03-03",
      "displayDate": "3 Marzo 2026",
      "description": "Nuova stagione della popolare serie anime.",
      "posterUrl": "https://image.tmdb.org/t/p/w500/7Uj6vqmznWQ3w3hpQ1eIY9mMyMw.jpg"
    },
    {
      "title": "Young Sherlock",
      "type": "tv",
      "platform": "Amazon Prime Video",
      "releaseDate": "2026-03-04",
      "displayDate": "4 Marzo 2026",
      "description": "Serie diretta da Guy Ritchie con Hero Fiennes Tiffin.",
      "posterUrl": "https://image.tmdb.org/t/p/w500/BMBWTgvL41sOYtfkmXen6nm9mG.jpg"
    },
    {
      "title": "The Foreigner",
      "type": "movie",
      "platform": "Sky (incl. NOW)",
      "releaseDate": "2026-03-04",
      "displayDate": "4 Marzo 2026",
      "description": "Film d'azione e thriller con Jackie Chan e Pierce Brosnan.",
      "posterUrl": "https://image.tmdb.org/t/p/w500/5w5jyiFDIgtgniX1SqSs9KMBDk7.jpg"
    },
    {
      "title": "Vladimir",
      "type": "tv",
      "platform": "Netflix",
      "releaseDate": "2026-03-05",
      "displayDate": "5 Marzo 2026",
      "description": "Una professoressa sviluppa una pericolosa ossessione per un nuovo affascinante collega.",
      "posterUrl": "https://image.tmdb.org/t/p/w500/j02VBIGVIk2OTwTUZ1YzyzcONAy.jpg"
    },
    {
      "title": "Grey's Anatomy Stagione 21 (nuovi episodi)",
      "type": "tv",
      "platform": "Disney+",
      "releaseDate": "2026-03-05",
      "displayDate": "5 Marzo 2026",
      "description": "Nuovi episodi dell'acclamato medical drama.",
      "posterUrl": ""
    },
    {
      "title": "La Lezione",
      "type": "movie",
      "platform": "Cinema in Italia",
      "releaseDate": "2026-03-05",
      "displayDate": "5 Marzo 2026",
      "description": "Thriller psicologico di Stefano Mordini con Matilda De Angelis e Stefano Accorsi.",
      "posterUrl": "https://image.tmdb.org/t/p/w500/4RRLD2tkiJ8YwNGAOv4ZS3Pp54z.jpg"
    },
    {
      "title": "Un Bel Giorno",
      "type": "movie",
      "platform": "Cinema in Italia",
      "releaseDate": "2026-03-05",
      "displayDate": "5 Marzo 2026",
      "description": "Commedia sentimentale di Fabio De Luigi con Virginia Raffaele.",
      "posterUrl": "https://image.tmdb.org/t/p/w500/lfl48xTTCWwXcXIYgi8XgRZyBlv.jpg"
    },
    {
      "title": "Jumpers - Un Salto tra gli Animali",
      "type": "movie",
      "platform": "Cinema in Italia",
      "releaseDate": "2026-03-05",
      "displayDate": "5 Marzo 2026",
      "description": "Film d'animazione Pixar.",
      "posterUrl": "https://image.tmdb.org/t/p/w500/2bGvWzmJNmCqXgSQ33Iif2xXLKe.jpg"
    },
    {
      "title": "La Sposa!",
      "type": "movie",
      "platform": "Cinema in Italia",
      "releaseDate": "2026-03-05",
      "displayDate": "5 Marzo 2026",
      "description": "Una storia tratta dall'universo di Frankenstein di Mary Shelley.",
      "posterUrl": "https://image.tmdb.org/t/p/w500/6CPov1YcWUByY32mASEiJaVatk0.jpg"
    },
    {
      "title": "War Machine",
      "type": "movie",
      "platform": "Netflix",
      "releaseDate": "2026-03-06",
      "displayDate": "6 Marzo 2026",
      "description": "L'addestramento di una squadra d'élite si trasforma in una lotta per la vita contro una minaccia inimmaginabile.",
      "posterUrl": "https://image.tmdb.org/t/p/w500/30t19PpvZ3GVw9nRsn7TjZh5qEr.jpg"
    },
    {
      "title": "The Beekeeper 2",
      "type": "movie",
      "platform": "Amazon Prime Video",
      "releaseDate": "2026-03-06",
      "displayDate": "6 Marzo 2026",
      "description": "Il sequel action con protagonista l'ex agente segreto.",
      "posterUrl": ""
    },
    {
      "title": "Shadow Force",
      "type": "movie",
      "platform": "Amazon Prime Video",
      "releaseDate": "2026-03-06",
      "displayDate": "6 Marzo 2026",
      "description": "Un film d'azione.",
      "posterUrl": "https://image.tmdb.org/t/p/w500/uX6FaNE86a4Xnf1mFFEryvjqB1D.jpg"
    },
    {
      "title": "Avvocato Ligas Stagione 1",
      "type": "tv",
      "platform": "Sky (incl. NOW)",
      "releaseDate": "2026-03-06",
      "displayDate": "6 Marzo 2026",
      "description": "Serie Sky Original con Luca Argentero nei panni di un avvocato penalista.",
      "posterUrl": ""
    },
    {
      "title": "Good Boy",
      "type": "movie",
      "platform": "Cinema in Italia",
      "releaseDate": "2026-03-06",
      "displayDate": "6 Marzo 2026",
      "description": "Film.",
      "posterUrl": "https://image.tmdb.org/t/p/w500/hKhElicngwgC2onW3m8HW8BpHGD.jpg"
    },
    {
      "title": "Ghost Elephants",
      "type": "movie",
      "platform": "Disney+",
      "releaseDate": "2026-03-08",
      "displayDate": "8 Marzo 2026",
      "description": "Docufilm.",
      "posterUrl": "https://image.tmdb.org/t/p/w500/kzgRatkRZvDci21ePraKKwiv2Yu.jpg"
    },
    {
      "title": "My Hero Academia: You're Next",
      "type": "movie",
      "platform": "Amazon Prime Video",
      "releaseDate": "2026-03-09",
      "displayDate": "9 Marzo 2026",
      "description": "Film anime esclusivo Prime.",
      "posterUrl": "https://image.tmdb.org/t/p/w500/cvqEQyFKnvwDOhPzpNBVJNZzftF.jpg"
    },
    {
      "title": "L'ultima sfida di Bruce Lee",
      "type": "movie",
      "platform": "Sky (incl. NOW)",
      "releaseDate": "2026-03-09",
      "displayDate": "9 Marzo 2026",
      "description": "Film d'azione e giallo.",
      "posterUrl": "https://image.tmdb.org/t/p/w500/7UO1YDhHvqBxpCRYnA8wDljwSbR.jpg"
    },
    {
      "title": "One Piece",
      "type": "tv",
      "platform": "Netflix",
      "releaseDate": "2026-03-10",
      "displayDate": "10 Marzo 2026",
      "description": "Seconda stagione dell'adattamento live-action del celebre manga.",
      "posterUrl": "https://image.tmdb.org/t/p/w500/mgrEi9VfRoN3bAuhf863f0sWC6A.jpg"
    },
    {
      "title": "Ida Red",
      "type": "movie",
      "platform": "Sky (incl. NOW)",
      "releaseDate": "2026-03-10",
      "displayDate": "10 Marzo 2026",
      "description": "Film d'azione e thriller con Frank Grillo e Josh Hartnett.",
      "posterUrl": "https://image.tmdb.org/t/p/w500/etMxKseW67499tUJonLNHXTF538.jpg"
    },
    {
      "title": "Scarpetta",
      "type": "tv",
      "platform": "Amazon Prime Video",
      "releaseDate": "2026-03-11",
      "displayDate": "11 Marzo 2026",
      "description": "Nicole Kidman interpreta la dottoressa Kay Scarpetta in questa serie mozzafiato.",
      "posterUrl": "https://image.tmdb.org/t/p/w500/6h8JXG3ffxb1l1DutYxyOAOuBhb.jpg"
    },
    {
      "title": "Solar Opposites",
      "type": "tv",
      "platform": "Disney+",
      "releaseDate": "2026-03-11",
      "displayDate": "11 Marzo 2026",
      "description": "Serie animata irriverente.",
      "posterUrl": "https://image.tmdb.org/t/p/w500/nuBD4dlO7gfg4RhW0sS0pTeiYRc.jpg"
    },
    {
      "title": "Zootropolis 2",
      "type": "movie",
      "platform": "Disney+",
      "releaseDate": "2026-03-11",
      "displayDate": "11 Marzo 2026",
      "description": "Film d'animazione.",
      "posterUrl": "https://image.tmdb.org/t/p/w500/lVesXbaSnCh0e27punAv4ZKWkxk.jpg"
    },
    {
      "title": "La vita segreta delle mogli Mormoni Stagione 4",
      "type": "tv",
      "platform": "Disney+",
      "releaseDate": "2026-03-12",
      "displayDate": "12 Marzo 2026",
      "description": "Docu-reality sulla vita delle mogli mormoni.",
      "posterUrl": ""
    },
    {
      "title": "Il Testamento di Ann Lee",
      "type": "movie",
      "platform": "Cinema in Italia",
      "releaseDate": "2026-03-12",
      "displayDate": "12 Marzo 2026",
      "description": "Film con Amanda Seyfried nei panni di Ann Lee, fondatrice degli Shakers.",
      "posterUrl": "https://image.tmdb.org/t/p/w500/kJwLIiIQP7Vp6shSGI7HBnv6Pxb.jpg"
    },
    {
      "title": "Quella notte",
      "type": "tv",
      "platform": "Netflix",
      "releaseDate": "2026-03-13",
      "displayDate": "13 Marzo 2026",
      "description": "Una serie thriller spagnola con Clara Galle, Claudia Salas e Paula Usero.",
      "posterUrl": "https://image.tmdb.org/t/p/w500/9Ew151KqBNn2yfIb8V0ZDL77Ke2.jpg"
    },
    {
      "title": "Reacher – Stagione 4",
      "type": "tv",
      "platform": "Amazon Prime Video",
      "releaseDate": "2026-03-14",
      "displayDate": "14 Marzo 2026",
      "description": "Il personaggio amato torna con una nuova indagine.",
      "posterUrl": ""
    },
    {
      "title": "Outlander Stagione 8",
      "type": "tv",
      "platform": "Sky (incl. NOW)",
      "releaseDate": "2026-03-14",
      "displayDate": "14 Marzo 2026",
      "description": "Stagione finale dell'epica storia d'amore.",
      "posterUrl": ""
    },
    {
      "title": "The Silent Sea – The Movie Cut",
      "type": "movie",
      "platform": "Amazon Prime Video",
      "releaseDate": "2026-03-15",
      "displayDate": "15 Marzo 2026",
      "description": "Versione cinematografica dell'acclamata serie sci-fi.",
      "posterUrl": ""
    },
    {
      "title": "Roofman",
      "type": "movie",
      "platform": "Amazon Prime Video",
      "releaseDate": "2026-03-16",
      "displayDate": "16 Marzo 2026",
      "description": "Un film in streaming.",
      "posterUrl": "https://image.tmdb.org/t/p/w500/wXDFtcnYtevleGzCmAD2ReQnJ4l.jpg"
    },
    {
      "title": "9-1-1 Stagione 9",
      "type": "tv",
      "platform": "Disney+",
      "releaseDate": "2026-03-18",
      "displayDate": "18 Marzo 2026",
      "description": "Nuova stagione della serie TV.",
      "posterUrl": ""
    },
    {
      "title": "Imperfect Women - Le mie amiche del cuore",
      "type": "movie",
      "platform": "Apple TV+",
      "releaseDate": "2026-03-18",
      "displayDate": "18 Marzo 2026",
      "description": "Un thriller psicologico con Elisabeth Moss, Kerry Washington e Kate Mara.",
      "posterUrl": ""
    },
    {
      "title": "Steel Ball Run - Le bizzarre avventure di Jojo",
      "type": "tv",
      "platform": "Netflix",
      "releaseDate": "2026-03-19",
      "displayDate": "19 Marzo 2026",
      "description": "Serie anime basata sul manga di Hirohiko Araki.",
      "posterUrl": "https://image.tmdb.org/t/p/w500/saqAUkE10gq9HYczLy5P4EDETfR.jpg"
    },
    {
      "title": "Notte prima degli esami 3.0",
      "type": "movie",
      "platform": "Cinema in Italia",
      "releaseDate": "2026-03-19",
      "displayDate": "19 Marzo 2026",
      "description": "Commedia.",
      "posterUrl": "https://image.tmdb.org/t/p/w500/akMWdGoPmiBNBTCX3WpMLr8q2u3.jpg"
    },
    {
      "title": "L'Ultima Missione - Project Hail Mary",
      "type": "movie",
      "platform": "Cinema in Italia",
      "releaseDate": "2026-03-19",
      "displayDate": "19 Marzo 2026",
      "description": "Film di fantascienza con Ryan Gosling.",
      "posterUrl": "https://image.tmdb.org/t/p/w500/gPC1X3mwqwX50Ye3qwwPt7iW3Ma.jpg"
    },
    {
      "title": "Peaky Blinders: The Immortal Man",
      "type": "movie",
      "platform": "Netflix",
      "releaseDate": "2026-03-20",
      "displayDate": "20 Marzo 2026",
      "description": "Un film legato all'universo dei Peaky Blinders.",
      "posterUrl": "https://image.tmdb.org/t/p/w500/4FXce93JqyDQl1B9lNv454Hs6qe.jpg"
    },
    {
      "title": "Red Notice: Global Heist",
      "type": "movie",
      "platform": "Amazon Prime Video",
      "releaseDate": "2026-03-20",
      "displayDate": "20 Marzo 2026",
      "description": "Il franchise action-comedy torna con una nuova missione internazionale.",
      "posterUrl": ""
    },
    {
      "title": "Elio",
      "type": "movie",
      "platform": "Disney+",
      "releaseDate": "2026-03-20",
      "displayDate": "20 Marzo 2026",
      "description": "Film d'animazione Pixar.",
      "posterUrl": "https://image.tmdb.org/t/p/w500/kFxz2c6cmINliKSLoUm4r6m0B2B.jpg"
    },
    {
      "title": "It Ends With Us - Siamo noi a dire basta",
      "type": "movie",
      "platform": "Netflix",
      "releaseDate": "2026-03-21",
      "displayDate": "21 Marzo 2026",
      "description": "La relazione di una donna è sconvolta dal ritorno del suo primo amore.",
      "posterUrl": "https://image.tmdb.org/t/p/w500/6KRRJpH9tImMs4z5W2JC1u2L5tX.jpg"
    },
    {
      "title": "The Boys: Origins",
      "type": "tv",
      "platform": "Amazon Prime Video",
      "releaseDate": "2026-03-22",
      "displayDate": "22 Marzo 2026",
      "description": "Spin-off ambientato nell'universo di The Boys.",
      "posterUrl": ""
    },
    {
      "title": "Lucky Luke",
      "type": "tv",
      "platform": "Disney+",
      "releaseDate": "2026-03-23",
      "displayDate": "23 Marzo 2026",
      "description": "Debutto della serie TV basata sul fumetto.",
      "posterUrl": "https://image.tmdb.org/t/p/w500/3dCO02aOGaKTdwDJaXtqlGa1GlF.jpg"
    },
    {
      "title": "Magicampers: Le avventure di Rosie e Cornélis",
      "type": "movie",
      "platform": "Disney+",
      "releaseDate": "2026-03-24",
      "displayDate": "24 Marzo 2026",
      "description": "Film d'animazione.",
      "posterUrl": ""
    },
    {
      "title": "Pretty Lethal",
      "type": "movie",
      "platform": "Amazon Prime Video",
      "releaseDate": "2026-03-25",
      "displayDate": "25 Marzo 2026",
      "description": "Un thriller.",
      "posterUrl": "https://image.tmdb.org/t/p/w500/znTPnXCK3lEQJgqXCvP7e5FUz6f.jpg"
    },
    {
      "title": "The Winter King",
      "type": "tv",
      "platform": "Amazon Prime Video",
      "releaseDate": "2026-03-25",
      "displayDate": "25 Marzo 2026",
      "description": "Una serie in streaming.",
      "posterUrl": "https://image.tmdb.org/t/p/w500/yfgc2Z4JmDq67quwOlpoqxTNnpb.jpg"
    },
    {
      "title": "Something Very Bad Is Going to Happen",
      "type": "tv",
      "platform": "Netflix",
      "releaseDate": "2026-03-26",
      "displayDate": "26 Marzo 2026",
      "description": "Una serie horror ambientata durante un matrimonio, che racconta la settimana precedente alle nozze.",
      "posterUrl": "https://image.tmdb.org/t/p/w500/eSEpYHECa5wXJGidUocJuYrALZP.jpg"
    },
    {
      "title": "Cattiva Strada",
      "type": "movie",
      "platform": "Cinema in Italia",
      "releaseDate": "2026-03-26",
      "displayDate": "26 Marzo 2026",
      "description": "Film.",
      "posterUrl": "https://image.tmdb.org/t/p/w500/i5aBrVSS6ksZ4zUQBYh9vdDqBZs.jpg"
    },
    {
      "title": "Mike & Nick & Nick & Alice",
      "type": "movie",
      "platform": "Disney+",
      "releaseDate": "2026-03-27",
      "displayDate": "27 Marzo 2026",
      "description": "Film.",
      "posterUrl": "https://image.tmdb.org/t/p/w500/FVYfy7sJLMS4ivsynwBnCWKFgw.jpg"
    },
    {
      "title": "For All Mankind Stagione 5",
      "type": "tv",
      "platform": "Apple TV+",
      "releaseDate": "2026-03-27",
      "displayDate": "27 Marzo 2026",
      "description": "Quinta stagione della serie di fantascienza.",
      "posterUrl": ""
    },
    {
      "title": "Venom 3: L'ultimo concerto",
      "type": "movie",
      "platform": "Amazon Prime Video",
      "releaseDate": "2026-03-30",
      "displayDate": "30 Marzo 2026",
      "description": "Film di supereroi.",
      "posterUrl": ""
    },
    {
      "title": "Your Friends and Neighbors Stagione 2",
      "type": "tv",
      "platform": "Apple TV+",
      "releaseDate": "2026-04-03",
      "displayDate": "3 Aprile 2026",
      "description": "Seconda stagione della serie drammatica con Jon Hamm.",
      "posterUrl": ""
    },
    {
      "title": "Beverly Hills, 90210",
      "type": "tv",
      "platform": "Sky (incl. NOW)",
      "releaseDate": "2026-04-03",
      "displayDate": "3 Aprile 2026",
      "description": "Tutte le dieci stagioni della serie teen drama.",
      "posterUrl": "https://image.tmdb.org/t/p/w500/b7BYfkhu653D894krwGO1ysIKTf.jpg"
    },
    {
      "title": "Outcome",
      "type": "movie",
      "platform": "Apple TV+",
      "releaseDate": "2026-04-10",
      "displayDate": "10 Aprile 2026",
      "description": "Film.",
      "posterUrl": "https://image.tmdb.org/t/p/w500/ln6AxyDbXI8UrH3CjR2XFo8wcdF.jpg"
    },
    {
      "title": "Euphoria Stagione 3",
      "type": "tv",
      "platform": "Sky (incl. NOW)",
      "releaseDate": "2026-04-13",
      "displayDate": "13 Aprile 2026",
      "description": "Terza stagione del dramma adolescenziale di Sam Levinson.",
      "posterUrl": ""
    },
    {
      "title": "Margo ha problemi di soldi",
      "type": "tv",
      "platform": "Apple TV+",
      "releaseDate": "2026-04-15",
      "displayDate": "15 Aprile 2026",
      "description": "Nuova serie che mescola ironia e dramma familiare.",
      "posterUrl": "https://image.tmdb.org/t/p/w500/5iVWUVfxOS1JFudntvPcLyHBw9y.jpg"
    },
    {
      "title": "BEEF Stagione 2",
      "type": "tv",
      "platform": "Netflix",
      "releaseDate": "2026-04-16",
      "displayDate": "16 Aprile 2026",
      "description": "Seconda stagione della serie acclamata.",
      "posterUrl": ""
    },
    {
      "title": "Criminal Record Stagione 2",
      "type": "tv",
      "platform": "Apple TV+",
      "releaseDate": "2026-04-22",
      "displayDate": "22 Aprile 2026",
      "description": "Seconda stagione della serie.",
      "posterUrl": ""
    },
    {
      "title": "Nel tepore del ballo",
      "type": "movie",
      "platform": "Cinema in Italia",
      "releaseDate": "2026-04-30",
      "displayDate": "30 Aprile 2026",
      "description": "Film di Pupi Avati.",
      "posterUrl": "https://image.tmdb.org/t/p/w500/ng9NBZ5qAJ4k4KlvQWgxKTuM1XT.jpg"
    },
    {
      "title": "Il diavolo veste Prada 2",
      "type": "movie",
      "platform": "Cinema in Italia",
      "releaseDate": "2026-04-30",
      "displayDate": "30 Aprile 2026",
      "description": "Sequel del celebre film sulla moda.",
      "posterUrl": "https://image.tmdb.org/t/p/w500/zDhu8axN365ytMTSHWxdK8WFH5t.jpg"
    },
    {
      "title": "Due spicci",
      "type": "tv",
      "platform": "Netflix",
      "releaseDate": "2026-05-01",
      "displayDate": "1 Maggio 2026",
      "description": "Nuova serie animata per adulti di Zerocalcare.",
      "posterUrl": "https://image.tmdb.org/t/p/w500/8ddADzGeoIxR3xubiMOn0d0yXsB.jpg"
    },
    {
      "title": "Mortal Kombat II",
      "type": "movie",
      "platform": "Cinema in Italia",
      "releaseDate": "2026-05-06",
      "displayDate": "6 Maggio 2026",
      "description": "Film d'azione, avventura, fantastico, fantascienza.",
      "posterUrl": "https://image.tmdb.org/t/p/w500/bN64Yvw4cU5LQBovuXxvjRMrUhU.jpg"
    },
    {
      "title": "Illusione",
      "type": "movie",
      "platform": "Cinema in Italia",
      "releaseDate": "2026-05-07",
      "displayDate": "7 Maggio 2026",
      "description": "Film drammatico di Francesca Archibugi.",
      "posterUrl": "https://image.tmdb.org/t/p/w500/cZRWBcAIfln9PpmSE6wCwf4KGLB.jpg"
    },
    {
      "title": "Billie Eilish: Hit Me Hard and Soft - The Tour (3D)",
      "type": "movie",
      "platform": "Cinema in Italia",
      "releaseDate": "2026-05-07",
      "displayDate": "7 Maggio 2026",
      "description": "Documentario musicale in 3D.",
      "posterUrl": "https://image.tmdb.org/t/p/w500/m9JQjDufp397fjWD0fh9LdbYhMg.jpg"
    },
    {
      "title": "Pecore sotto copertura",
      "type": "movie",
      "platform": "Cinema in Italia",
      "releaseDate": "2026-05-07",
      "displayDate": "7 Maggio 2026",
      "description": "Film d'azione, commedia, giallo.",
      "posterUrl": "https://image.tmdb.org/t/p/w500/6QtL9rl3Zb4d8qW6EJ4qO5hSSfU.jpg"
    },
    {
      "title": "Rosa elettrica",
      "type": "tv",
      "platform": "Sky (incl. NOW)",
      "releaseDate": "2026-05-08",
      "displayDate": "8 Maggio 2026",
      "description": "Serie thriller.",
      "posterUrl": ""
    },
    {
      "title": "Tre chilometri alla fine del mondo",
      "type": "movie",
      "platform": "Cinema in Italia",
      "releaseDate": "2026-05-13",
      "displayDate": "13 Maggio 2026",
      "description": "Film drammatico e thriller.",
      "posterUrl": ""
    },
    {
      "title": "Star Wars: The Mandalorian and Grogu",
      "type": "movie",
      "platform": "Cinema in Italia",
      "releaseDate": "2026-05-20",
      "displayDate": "20 Maggio 2026",
      "description": "Film dell'universo di Star Wars con Pedro Pascal e Grogu.",
      "posterUrl": "https://image.tmdb.org/t/p/w500/2XX2XlXdfEWV0tfUyWunBj1SFpx.jpg"
    },
    {
      "title": "Backrooms",
      "type": "movie",
      "platform": "Cinema in Italia",
      "releaseDate": "2026-05-27",
      "displayDate": "27 Maggio 2026",
      "description": "Film horror diretto da Kane Parsons.",
      "posterUrl": "https://image.tmdb.org/t/p/w500/sYn6PHN0PE6ep3TGlYS5bM3AkPg.jpg"
    }
  ]
}