{
  "date": "12/04/2026, 08:22:02",
  "data": [
    {
      "title": "The Handmaid's Tale – Sesta Stagione",
      "type": "tv",
      "platform": "Amazon Prime Video",
      "releaseDate": "2026-04-01",
      "displayDate": "1 Aprile 2026",
      "description": "Sesta stagione della serie distopica.",
      "posterUrl": ""
    },
    {
      "title": "Crime 101 – La strada del crimine",
      "type": "movie",
      "platform": "Amazon Prime Video",
      "releaseDate": "2026-04-01",
      "displayDate": "1 Aprile 2026",
      "description": "Film.",
      "posterUrl": "https://image.tmdb.org/t/p/w500/ouD5CS3DPyarfQkJf5kWF6akptZ.jpg"
    },
    {
      "title": "C'è ancora domani",
      "type": "movie",
      "platform": "Amazon Prime Video",
      "releaseDate": "2026-04-01",
      "displayDate": "1 Aprile 2026",
      "description": "Film.",
      "posterUrl": "https://image.tmdb.org/t/p/w500/hc9SHN0vB6iyr6MBYI6bKrpDHvJ.jpg"
    },
    {
      "title": "Material Love",
      "type": "movie",
      "platform": "Amazon Prime Video",
      "releaseDate": "2026-04-01",
      "displayDate": "1 Aprile 2026",
      "description": "Film romantico/drammatico con Dakota Johnson, su un'organizzatrice di appuntamenti.",
      "posterUrl": "https://image.tmdb.org/t/p/w500/nmNi5uMO5earkzK9OL0nsWMQOr7.jpg"
    },
    {
      "title": "Love Me Love Me",
      "type": "movie",
      "platform": "Amazon Prime Video",
      "releaseDate": "2026-04-01",
      "displayDate": "1 Aprile 2026",
      "description": "Film Prime Original italiano su una ragazza che si trasferisce in Italia dopo la morte del fratello.",
      "posterUrl": "https://image.tmdb.org/t/p/w500/jfwHKRHRE2X4NTexdzblaioHH51.jpg"
    },
    {
      "title": "Dear Killer Nannies",
      "type": "tv",
      "platform": "Disney+",
      "releaseDate": "2026-04-01",
      "displayDate": "1 Aprile 2026",
      "description": "Serie TV in cui un bambino scopre che le sue amate baby sitter sono sicari e suo padre è Pablo Escobar.",
      "posterUrl": "https://image.tmdb.org/t/p/w500/tcO7iKyaEvyR5YDbgecCsEizbq2.jpg"
    },
    {
      "title": "I segreti delle api",
      "type": "tv",
      "platform": "Disney+",
      "releaseDate": "2026-04-01",
      "displayDate": "1 Aprile 2026",
      "description": "Nuova serie originale di National Geographic che rivela lo straordinario mondo delle api.",
      "posterUrl": "https://image.tmdb.org/t/p/w500/60V1dxBjJTMqwnL2Us4RAZS4giv.jpg"
    },
    {
      "title": "Il Maestro",
      "type": "movie",
      "platform": "Sky (incl. NOW)",
      "releaseDate": "2026-04-01",
      "displayDate": "1 Aprile 2026",
      "description": "Film.",
      "posterUrl": "https://image.tmdb.org/t/p/w500/oDucYHSU6iDlRKAj0tJmvNBgoq0.jpg"
    },
    {
      "title": "Troppo cattivi 2",
      "type": "movie",
      "platform": "Sky (incl. NOW)",
      "releaseDate": "2026-04-01",
      "displayDate": "1 Aprile 2026",
      "description": "Film.",
      "posterUrl": "https://image.tmdb.org/t/p/w500/gYuaju3hqkcxRjlCPgXlW2zthXT.jpg"
    },
    {
      "title": "Io sono nessuno 2",
      "type": "movie",
      "platform": "Sky (incl. NOW)",
      "releaseDate": "2026-04-01",
      "displayDate": "1 Aprile 2026",
      "description": "Film.",
      "posterUrl": "https://image.tmdb.org/t/p/w500/8RXDbeVG9Tb0z8FWPph77uJsTkd.jpg"
    },
    {
      "title": "Father Mother Sister Brother",
      "type": "movie",
      "platform": "Sky (incl. NOW)",
      "releaseDate": "2026-04-01",
      "displayDate": "1 Aprile 2026",
      "description": "Film di Jim Jarmusch, Leone d'Oro alla Mostra del Cinema di Venezia 2025, racconta le relazioni tra figli, fratelli e genitori distanti.",
      "posterUrl": "https://image.tmdb.org/t/p/w500/96O3Ol3f2veMxAxYqsML8rOumB9.jpg"
    },
    {
      "title": "Amata",
      "type": "movie",
      "platform": "Sky (incl. NOW)",
      "releaseDate": "2026-04-01",
      "displayDate": "1 Aprile 2026",
      "description": "Film.",
      "posterUrl": "https://image.tmdb.org/t/p/w500/tP036DZlwH3wt2pQW9yvBFUYDXF.jpg"
    },
    {
      "title": "La voce di Hind Rajab",
      "type": "movie",
      "platform": "Sky (incl. NOW)",
      "releaseDate": "2026-04-01",
      "displayDate": "1 Aprile 2026",
      "description": "Film.",
      "posterUrl": "https://image.tmdb.org/t/p/w500/dxMJK7Ugfs7M0Ac9qFIHsmeX3k2.jpg"
    },
    {
      "title": "The Super Mario Galaxy Movie",
      "type": "movie",
      "platform": "Cinema in Italia",
      "releaseDate": "2026-04-01",
      "displayDate": "1 Aprile 2026",
      "description": "Secondo capitolo animato dedicato all'idraulico più celebre dei videogame.",
      "posterUrl": "https://image.tmdb.org/t/p/w500/pxH7Hqg8dSROSunEQyUPLtTeEQy.jpg"
    },
    {
      "title": "Troppo cattivi: La serie",
      "type": "tv",
      "platform": "Netflix",
      "releaseDate": "2026-04-02",
      "displayDate": "2 Aprile 2026",
      "description": "Serie animata.",
      "posterUrl": "https://image.tmdb.org/t/p/w500/dIZtcY364JCXwKCYpNE2nl5JWwt.jpg"
    },
    {
      "title": "XO, Kitty stagione 3",
      "type": "tv",
      "platform": "Netflix",
      "releaseDate": "2026-04-02",
      "displayDate": "2 Aprile 2026",
      "description": "Terza stagione della serie TV.",
      "posterUrl": ""
    },
    {
      "title": "I peccati di Kujo",
      "type": "tv",
      "platform": "Netflix",
      "releaseDate": "2026-04-02",
      "displayDate": "2 Aprile 2026",
      "description": "Serie TV.",
      "posterUrl": "https://image.tmdb.org/t/p/w500/1eHY0eqE6ricIouCyxMfAFm6D6i.jpg"
    },
    {
      "title": "Pizza Movie",
      "type": "movie",
      "platform": "Disney+",
      "releaseDate": "2026-04-02",
      "displayDate": "2 Aprile 2026",
      "description": "Commedia del 2026 su due giovani coinquilini che si ritrovano in un'avventura spericolata.",
      "posterUrl": "https://image.tmdb.org/t/p/w500/2c2ib9pS3BTIoMnYHi4z6t9nxuA.jpg"
    },
    {
      "title": "Non abbiam bisogno di parole",
      "type": "movie",
      "platform": "Netflix",
      "releaseDate": "2026-04-03",
      "displayDate": "3 Aprile 2026",
      "description": "Film italiano che segna l'esordio alla recitazione di Sarah Toscano, narra una storia intensa a metà tra musica e dramma, dove la protagonista scopre un talento vocale fuori dal comune.",
      "posterUrl": "https://image.tmdb.org/t/p/w500/ptWVRyHpDYDoU1vWR2jBQOFSE24.jpg"
    },
    {
      "title": "The Bad Boy and Me 2",
      "type": "movie",
      "platform": "Amazon Prime Video",
      "releaseDate": "2026-04-03",
      "displayDate": "3 Aprile 2026",
      "description": "Film.",
      "posterUrl": "https://image.tmdb.org/t/p/w500/sEIP1pTVXa8BJaYSuVeVG3wFN10.jpg"
    },
    {
      "title": "Your Friends and Neighbors 2",
      "type": "tv",
      "platform": "Apple TV+",
      "releaseDate": "2026-04-03",
      "displayDate": "3 Aprile 2026",
      "description": "La seconda stagione riprenderà la storia di Andrew Cooper, che continua a condurre la sua doppia vita.",
      "posterUrl": ""
    },
    {
      "title": "Beverly Hills 90210",
      "type": "tv",
      "platform": "Sky (incl. NOW)",
      "releaseDate": "2026-04-03",
      "displayDate": "3 Aprile 2026",
      "description": "Tutte le dieci stagioni della serie che ha ispirato i teen drama.",
      "posterUrl": "https://image.tmdb.org/t/p/w500/b7BYfkhu653D894krwGO1ysIKTf.jpg"
    },
    {
      "title": "Star Wars: Maul - Shadow Lord",
      "type": "tv",
      "platform": "Disney+",
      "releaseDate": "2026-04-06",
      "displayDate": "6 Aprile 2026",
      "description": "Serie animata ambientata dopo gli eventi di Star Wars: The Clone Wars, mostra Maul che trama per ricostruire il suo sindacato criminale.",
      "posterUrl": "https://image.tmdb.org/t/p/w500/fTfLd3s9yBNOzbFHD2aXvwEs93H.jpg"
    },
    {
      "title": "Untold: I re degli scacchi",
      "type": "movie",
      "platform": "Netflix",
      "releaseDate": "2026-04-07",
      "displayDate": "7 Aprile 2026",
      "description": "Documentario che esplora lo scontro tra Magnus Carlsen e Hans Niemann e le accuse di cheating.",
      "posterUrl": "https://image.tmdb.org/t/p/w500/cJYeU0UhPKQ8IoM8qXQ64aYHWJ0.jpg"
    },
    {
      "title": "The Testaments",
      "type": "tv",
      "platform": "Disney+",
      "releaseDate": "2026-04-08",
      "displayDate": "8 Aprile 2026",
      "description": "Drammatica storia di formazione a Gilead, evoluzione de 'Il racconto dell'ancella'.",
      "posterUrl": "https://image.tmdb.org/t/p/w500/xVsFopLisBoiKdXXecaNTN4pJ9A.jpg"
    },
    {
      "title": "Malcolm: Che vita!",
      "type": "tv",
      "platform": "Disney+",
      "releaseDate": "2026-04-10",
      "displayDate": "10 Aprile 2026",
      "description": "Revival dell'iconica serie dei primi anni 2000.",
      "posterUrl": "https://image.tmdb.org/t/p/w500/42Flvv5SNXtyLtezGxfinDKvSyk.jpg"
    },
    {
      "title": "Outcome - Hollywood non dimentica",
      "type": "movie",
      "platform": "Apple TV+",
      "releaseDate": "2026-04-10",
      "displayDate": "10 Aprile 2026",
      "description": "Commedia dark con Keanu Reeves.",
      "posterUrl": "https://image.tmdb.org/t/p/w500/ln6AxyDbXI8UrH3CjR2XFo8wcdF.jpg"
    },
    {
      "title": "Euphoria s.3",
      "type": "tv",
      "platform": "Sky (incl. NOW)",
      "releaseDate": "2026-04-13",
      "displayDate": "13 Aprile 2026",
      "description": "Terza stagione della serie TV.",
      "posterUrl": ""
    },
    {
      "title": "La legge di Lidia Poët 3",
      "type": "tv",
      "platform": "Netflix",
      "releaseDate": "2026-04-15",
      "displayDate": "15 Aprile 2026",
      "description": "Il capitolo conclusivo della serie che vede Matilda De Angelis vestire i panni della prima avvocata d'Italia.",
      "posterUrl": ""
    },
    {
      "title": "Margo ha problemi di soldi",
      "type": "tv",
      "platform": "Apple TV+",
      "releaseDate": "2026-04-15",
      "displayDate": "15 Aprile 2026",
      "description": "Serie con Elle Fanning e Michelle Pfeiffer, una storia di relazioni familiari, problemi e wrestling.",
      "posterUrl": "https://image.tmdb.org/t/p/w500/9UO47ekDKvWJ7uW3fesato0fMQ4.jpg"
    },
    {
      "title": "Beef – Lo scontro 2",
      "type": "tv",
      "platform": "Netflix",
      "releaseDate": "2026-04-16",
      "displayDate": "16 Aprile 2026",
      "description": "Seconda stagione della serie antologica, presenta una storia completamente nuova ambientata nel mondo elitario di un country club.",
      "posterUrl": ""
    },
    {
      "title": "Mr. Nobody Against Putin",
      "type": "movie",
      "platform": "Cinema in Italia",
      "releaseDate": "2026-04-16",
      "displayDate": "16 Aprile 2026",
      "description": "Film premio Oscar 2026.",
      "posterUrl": "https://image.tmdb.org/t/p/w500/vxvYpq92BRYlsJmSroswNoiDbnR.jpg"
    },
    {
      "title": "Orango",
      "type": "movie",
      "platform": "Disney+",
      "releaseDate": "2026-04-22",
      "displayDate": "22 Aprile 2026",
      "description": "Documentario.",
      "posterUrl": "https://image.tmdb.org/t/p/w500/mfbtDMwiPzVZZGIRCY6MPwdt8WY.jpg"
    },
    {
      "title": "Criminal Record 2",
      "type": "tv",
      "platform": "Apple TV+",
      "releaseDate": "2026-04-22",
      "displayDate": "22 Aprile 2026",
      "description": "Seconda stagione della potente serie drama incentrata sui personaggi e ambientata nel cuore della Londra contemporanea.",
      "posterUrl": ""
    },
    {
      "title": "Stranger Things: Storie dal 1985",
      "type": "tv",
      "platform": "Netflix",
      "releaseDate": "2026-04-23",
      "displayDate": "23 Aprile 2026",
      "description": "Serie animata prodotta dai Duffer Brothers, ambientata nel rigido inverno del 1985 a Hawkins.",
      "posterUrl": "https://image.tmdb.org/t/p/w500/2orq3F4a1prP3RnJjYSWzSjHYZQ.jpg"
    },
    {
      "title": "LOL: Chi ride è fuori S6",
      "type": "tv",
      "platform": "Amazon Prime Video",
      "releaseDate": "2026-04-23",
      "displayDate": "23 Aprile 2026",
      "description": "La nuova stagione del comedy show in 6 episodi.",
      "posterUrl": ""
    },
    {
      "title": "Michael",
      "type": "movie",
      "platform": "Cinema in Italia",
      "releaseDate": "2026-04-23",
      "displayDate": "23 Aprile 2026",
      "description": "Biopic che racconta la vita di Michael Jackson.",
      "posterUrl": "https://image.tmdb.org/t/p/w500/3Qud19bBUrrJAzy0Ilm8gRJlJXP.jpg"
    },
    {
      "title": "Un minotauro per fratello",
      "type": "movie",
      "platform": "Apple TV+",
      "releaseDate": "2026-04-24",
      "displayDate": "24 Aprile 2026",
      "description": "Film d'animazione.",
      "posterUrl": ""
    },
    {
      "title": "The Boys S5",
      "type": "tv",
      "platform": "Amazon Prime Video",
      "releaseDate": "2026-04-29",
      "displayDate": "29 Aprile 2026",
      "description": "Quinta stagione della serie TV.",
      "posterUrl": ""
    },
    {
      "title": "La casa degli Spiriti",
      "type": "tv",
      "platform": "Amazon Prime Video",
      "releaseDate": "2026-04-29",
      "displayDate": "29 Aprile 2026",
      "description": "Miniserie.",
      "posterUrl": ""
    },
    {
      "title": "Widow's Bay",
      "type": "tv",
      "platform": "Apple TV+",
      "releaseDate": "2026-04-29",
      "displayDate": "29 Aprile 2026",
      "description": "Serie TV.",
      "posterUrl": "https://image.tmdb.org/t/p/w500/5lcxWLVAEICkFpuAiV1aMy7ZZj3.jpg"
    },
    {
      "title": "Man on Fire - Sete di vendetta",
      "type": "tv",
      "platform": "Netflix",
      "releaseDate": "2026-04-30",
      "displayDate": "30 Aprile 2026",
      "description": "Serie TV.",
      "posterUrl": "https://image.tmdb.org/t/p/w500/d3nPGZqPWXKmqMGVM3zBCyWLVGP.jpg"
    },
    {
      "title": "Due spicci",
      "type": "tv",
      "platform": "Netflix",
      "releaseDate": "2026-05-01",
      "displayDate": "1 Maggio 2026",
      "description": "Serie di Zerocalcare, i personaggi hanno trovato il loro posto nel mondo ma scoprono quanto sia difficile mantenerlo.",
      "posterUrl": "https://image.tmdb.org/t/p/w500/6x2Jn045qsaevVtUuCKBjrDBwD3.jpg"
    },
    {
      "title": "Il principe della follia",
      "type": "movie",
      "platform": "Cinema in Italia",
      "releaseDate": "2026-05-01",
      "displayDate": "1 Maggio 2026",
      "description": "Film.",
      "posterUrl": "https://image.tmdb.org/t/p/w500/7bucjBjFRIvzxHuL3UFOuYeWdiL.jpg"
    },
    {
      "title": "Tuner - L'Accordatore",
      "type": "movie",
      "platform": "Cinema in Italia",
      "releaseDate": "2026-05-01",
      "displayDate": "1 Maggio 2026",
      "description": "Film.",
      "posterUrl": "https://image.tmdb.org/t/p/w500/oGZd4xQJBt4mtuBhTdlOalsdqtT.jpg"
    },
    {
      "title": "Illusione",
      "type": "movie",
      "platform": "Cinema in Italia",
      "releaseDate": "2026-05-01",
      "displayDate": "1 Maggio 2026",
      "description": "Film.",
      "posterUrl": "https://image.tmdb.org/t/p/w500/cZRWBcAIfln9PpmSE6wCwf4KGLB.jpg"
    },
    {
      "title": "Millennium Actress",
      "type": "movie",
      "platform": "Cinema in Italia",
      "releaseDate": "2026-05-01",
      "displayDate": "1 Maggio 2026",
      "description": "Film.",
      "posterUrl": "https://image.tmdb.org/t/p/w500/hlblOom21GZFdygnRr3OXIrz5O.jpg"
    },
    {
      "title": "Willie Peyote - Elegia Sabauda",
      "type": "movie",
      "platform": "Cinema in Italia",
      "releaseDate": "2026-05-01",
      "displayDate": "1 Maggio 2026",
      "description": "Film.",
      "posterUrl": "https://image.tmdb.org/t/p/w500/o2Hc5N8FQhaNcEpD297QCwimKBG.jpg"
    },
    {
      "title": "Mortal Kombat II",
      "type": "movie",
      "platform": "Cinema in Italia",
      "releaseDate": "2026-05-01",
      "displayDate": "1 Maggio 2026",
      "description": "Film.",
      "posterUrl": "https://image.tmdb.org/t/p/w500/lIsMeDbwntNXSUVHmWMMRXEZOVc.jpg"
    },
    {
      "title": "Legends",
      "type": "tv",
      "platform": "Netflix",
      "releaseDate": "2026-05-07",
      "displayDate": "7 Maggio 2026",
      "description": "Serie TV drammatica/crime ispirata a una storia vera, sulla droga nella Gran Bretagna degli anni '90.",
      "posterUrl": "https://image.tmdb.org/t/p/w500/gXZbSYN3i2DjHKJORZiBf8P9LDF.jpg"
    },
    {
      "title": "Unconditional",
      "type": "movie",
      "platform": "Apple TV+",
      "releaseDate": "2026-05-08",
      "displayDate": "8 Maggio 2026",
      "description": "Film.",
      "posterUrl": "https://image.tmdb.org/t/p/w500/utD4YdrlyktHAAM7Qt7hq4UppLX.jpg"
    },
    {
      "title": "Rivals",
      "type": "tv",
      "platform": "Disney+",
      "releaseDate": "2026-05-15",
      "displayDate": "15 Maggio 2026",
      "description": "Serie TV ambientata nella Gran Bretagna del 1986, nel mondo spietato della televisione.",
      "posterUrl": "https://image.tmdb.org/t/p/w500/n1U5jlDDRaEylEUVbu6mtVbCAUL.jpg"
    },
    {
      "title": "Maximum Pleasure Guaranteed",
      "type": "movie",
      "platform": "Apple TV+",
      "releaseDate": "2026-05-20",
      "displayDate": "20 Maggio 2026",
      "description": "Commedia thriller con Tatiana Maslany.",
      "posterUrl": ""
    },
    {
      "title": "The Mandalorian & Grogu",
      "type": "movie",
      "platform": "Cinema in Italia",
      "releaseDate": "2026-05-20",
      "displayDate": "20 Maggio 2026",
      "description": "Film che riporta al cinema l'universo seriale di Star Wars.",
      "posterUrl": "https://image.tmdb.org/t/p/w500/2XX2XlXdfEWV0tfUyWunBj1SFpx.jpg"
    },
    {
      "title": "Star City",
      "type": "tv",
      "platform": "Apple TV+",
      "releaseDate": "2026-05-29",
      "displayDate": "29 Maggio 2026",
      "description": "Serie TV che amplia il mondo di For All Mankind.",
      "posterUrl": "https://image.tmdb.org/t/p/w500/mCP8HkmZBXaU91MqMCxJrOO5WXK.jpg"
    },
    {
      "title": "Poker Face s.1",
      "type": "tv",
      "platform": "Sky (incl. NOW)",
      "releaseDate": "2026-05-29",
      "displayDate": "29 Maggio 2026",
      "description": "Prima stagione della serie TV.",
      "posterUrl": ""
    },
    {
      "title": "Not Suitable for Work",
      "type": "tv",
      "platform": "Disney+",
      "releaseDate": "2026-06-02",
      "displayDate": "2 Giugno 2026",
      "description": "Nuova serie comedy originale creata da Mindy Kaling, segue cinque ventenni ossessionati dal lavoro.",
      "posterUrl": ""
    },
    {
      "title": "Every Year After",
      "type": "tv",
      "platform": "Amazon Prime Video",
      "releaseDate": "2026-06-10",
      "displayDate": "10 Giugno 2026",
      "description": "Serie TV.",
      "posterUrl": ""
    },
    {
      "title": "Nessun titolo confermato",
      "type": "N/A",
      "platform": "Discovery+",
      "releaseDate": "N/A",
      "displayDate": "N/A",
      "description": "Nessun titolo confermato per il periodo dal 1 Aprile 2026 al 30 Giugno 2026.",
      "posterUrl": ""
    }
  ]
}