{
  "date": "14/04/2026, 10:20:12",
  "data": [
    {
      "title": "Crime 101 - La strada del crimine",
      "type": "movie",
      "platform": "Amazon Prime Video",
      "rank": 1,
      "description": "Un thriller avvincente che vede incrociarsi i destini di un ladro di gioielli, un detective e una broker assicurativa.",
      "posterUrl": "https://image.tmdb.org/t/p/w500/ouD5CS3DPyarfQkJf5kWF6akptZ.jpg"
    },
    {
      "title": "A Big Bold Beautiful Journey",
      "type": "movie",
      "platform": "Amazon Prime Video",
      "rank": 2,
      "description": "Un film che mescola romanticismo e atmosfere surreali con Colin Farrell e Margot Robbie.",
      "posterUrl": "https://image.tmdb.org/t/p/w500/lpPuRtHFgwb44kXkPCsO6392Zez.jpg"
    },
    {
      "title": "Material Love",
      "type": "movie",
      "platform": "Amazon Prime Video",
      "rank": 3,
      "description": "Una commedia romantica con Dakota Johnson nei panni di una matchmaker di successo.",
      "posterUrl": "https://image.tmdb.org/t/p/w500/nmNi5uMO5earkzK9OL0nsWMQOr7.jpg"
    },
    {
      "title": "Mercy: sotto accusa",
      "type": "movie",
      "platform": "Amazon Prime Video",
      "rank": 4,
      "description": "Un film drammatico/crime popolare sulla piattaforma.",
      "posterUrl": "https://image.tmdb.org/t/p/w500/zhNy3atrXo4DOwmbWbWJx1qy9Wh.jpg"
    },
    {
      "title": "Reacher",
      "type": "tv",
      "platform": "Amazon Prime Video",
      "rank": 5,
      "description": "Una serie d'azione basata sui romanzi di Lee Child, tra le più viste.",
      "posterUrl": "https://image.tmdb.org/t/p/w500/31GlRQMiDunO8cl3NxTz34U64rf.jpg"
    },
    {
      "title": "From",
      "type": "tv",
      "platform": "Amazon Prime Video",
      "rank": 6,
      "description": "Una serie horror-mistery che svela il mistero di una cittadina che intrappola chiunque vi entri.",
      "posterUrl": "https://image.tmdb.org/t/p/w500/oRTAA5VqHi2W2rfkiJ3fHiGfI9M.jpg"
    },
    {
      "title": "INVINCIBLE",
      "type": "tv",
      "platform": "Amazon Prime Video",
      "rank": 7,
      "description": "Una serie animata di supereroi con nuovi episodi in tendenza.",
      "posterUrl": "https://image.tmdb.org/t/p/w500/4tblBrslcKSifMVZ3TmtT2ukMor.jpg"
    },
    {
      "title": "Mission: Impossible - The Final Reckoning",
      "type": "movie",
      "platform": "Amazon Prime Video",
      "rank": 8,
      "description": "L'ultimo capitolo della celebre saga di spionaggio e azione.",
      "posterUrl": "https://image.tmdb.org/t/p/w500/bhBHcUBEGEuEu9iVEgDlSsQIn5l.jpg"
    },
    {
      "title": "Pretty Lethal - Ballerine all'inferno",
      "type": "movie",
      "platform": "Amazon Prime Video",
      "rank": 9,
      "description": "Un thriller ambientato nel mondo della danza, dove cinque ballerine si ritrovano in un incubo.",
      "posterUrl": "https://image.tmdb.org/t/p/w500/oqFoq1tiXKlKN1pDd7tvizOsQPe.jpg"
    },
    {
      "title": "Agente Zeta",
      "type": "movie",
      "platform": "Amazon Prime Video",
      "rank": 10,
      "description": "Un nuovo film d'azione in tendenza sulla piattaforma.",
      "posterUrl": "https://image.tmdb.org/t/p/w500/9cbleJ3OV26wzzIkVjyfsh866pD.jpg"
    },
    {
      "title": "Outcome",
      "type": "movie",
      "platform": "Apple TV+",
      "rank": 1,
      "description": "Una commedia che si posiziona al primo posto tra i contenuti più popolari.",
      "posterUrl": "https://image.tmdb.org/t/p/w500/ln6AxyDbXI8UrH3CjR2XFo8wcdF.jpg"
    },
    {
      "title": "My Tennis Maestro",
      "type": "tv",
      "platform": "Apple TV+",
      "rank": 2,
      "description": "Una serie drammatica che esplora il mondo del tennis.",
      "posterUrl": ""
    },
    {
      "title": "F1 The Movie",
      "type": "movie",
      "platform": "Apple TV+",
      "rank": 3,
      "description": "Un film d'azione dedicato al mondo della Formula 1.",
      "posterUrl": ""
    },
    {
      "title": "Greyhound",
      "type": "movie",
      "platform": "Apple TV+",
      "rank": 4,
      "description": "Un thriller d'azione ambientato durante la Seconda Guerra Mondiale con Tom Hanks.",
      "posterUrl": "https://image.tmdb.org/t/p/w500/iJBLPfZkYF5tphFeEULjOMCgwlR.jpg"
    },
    {
      "title": "Eternity",
      "type": "movie",
      "platform": "Apple TV+",
      "rank": 5,
      "description": "Un film romantico tra i più visti sulla piattaforma.",
      "posterUrl": "https://image.tmdb.org/t/p/w500/yz01yDGw9STzqTE8kSmRMbOiLo7.jpg"
    },
    {
      "title": "The Gorge",
      "type": "movie",
      "platform": "Apple TV+",
      "rank": 6,
      "description": "Un film thriller che cattura l'attenzione del pubblico.",
      "posterUrl": "https://image.tmdb.org/t/p/w500/7IU0AhsnulBMEGauba755Snhcy4.jpg"
    },
    {
      "title": "Fountain of Youth",
      "type": "movie",
      "platform": "Apple TV+",
      "rank": 7,
      "description": "Un film d'azione che esplora il tema dell'eterna giovinezza.",
      "posterUrl": "https://image.tmdb.org/t/p/w500/kCWGK8QoK8ZPt6sju8pjohG4oxv.jpg"
    },
    {
      "title": "The Instigators",
      "type": "movie",
      "platform": "Apple TV+",
      "rank": 8,
      "description": "Un film d'azione che figura tra i titoli più popolari.",
      "posterUrl": "https://image.tmdb.org/t/p/w500/6wXRANRmPRmwbgzpvMuRKasWQNo.jpg"
    },
    {
      "title": "Napoleon",
      "type": "movie",
      "platform": "Apple TV+",
      "rank": 9,
      "description": "Un dramma storico che ripercorre la vita di Napoleone Bonaparte.",
      "posterUrl": "https://image.tmdb.org/t/p/w500/5Meo32HdrjIyN7Ne8vxBiPg2nSl.jpg"
    },
    {
      "title": "Shrinking",
      "type": "tv",
      "platform": "Apple TV+",
      "rank": 10,
      "description": "Una serie comedy che segue un terapista in lutto che inizia a dire ai suoi pazienti esattamente cosa pensa.",
      "posterUrl": "https://image.tmdb.org/t/p/w500/zEFKMNPBKq6JG7uuDkzTQ9WwErn.jpg"
    },
    {
      "title": "Feel My Voice",
      "type": "movie",
      "platform": "Netflix",
      "rank": 1,
      "description": "Un film drammatico musicale sudcoreano che esplora temi di musica e crescita personale.",
      "posterUrl": "https://image.tmdb.org/t/p/w500/ptWVRyHpDYDoU1vWR2jBQOFSE24.jpg"
    },
    {
      "title": "The Killer",
      "type": "movie",
      "platform": "Netflix",
      "rank": 2,
      "description": "L'acclamato thriller di David Fincher che segue un assassino solitario alle prese con le conseguenze di un errore.",
      "posterUrl": "https://image.tmdb.org/t/p/w500/oiQCURaDK9b0Z9RVeNuyu0UFi63.jpg"
    },
    {
      "title": "KPop Demon Hunters",
      "type": "movie",
      "platform": "Netflix",
      "rank": 3,
      "description": "Un'action-comedy musicale animata che ha scalato le classifiche.",
      "posterUrl": "https://image.tmdb.org/t/p/w500/uPkg9Wz1WEWQZoHkNNe3Dc49z0t.jpg"
    },
    {
      "title": "Humint",
      "type": "movie",
      "platform": "Netflix",
      "rank": 4,
      "description": "Un thriller che si è posizionato al primo posto tra i film più visti.",
      "posterUrl": "https://image.tmdb.org/t/p/w500/f7sCSLEPRfV2fWQ0RYOtHhnHXuG.jpg"
    },
    {
      "title": "The Rip - Soldi sporchi",
      "type": "movie",
      "platform": "Netflix",
      "rank": 5,
      "description": "Un nuovo film crime con Matt Damon e Ben Affleck, su una squadra di poliziotti che trova un deposito di contanti.",
      "posterUrl": "https://image.tmdb.org/t/p/w500/oY5JK04G4MzyhlXOQQyXaflEdB6.jpg"
    },
    {
      "title": "Squid Game",
      "type": "tv",
      "platform": "Netflix",
      "rank": 6,
      "description": "La popolarissima serie drammatica sudcoreana di sopravvivenza.",
      "posterUrl": "https://image.tmdb.org/t/p/w500/nW5rupC5zMeAGgGBYXkr8JL8Xq7.jpg"
    },
    {
      "title": "Mercoledì (Wednesday)",
      "type": "tv",
      "platform": "Netflix",
      "rank": 7,
      "description": "La popolare serie mystery-comedy soprannaturale incentrata sul personaggio di Mercoledì Addams.",
      "posterUrl": "https://image.tmdb.org/t/p/w500/sci4aAuTCWQsIs2uo7LoZVtMdD0.jpg"
    },
    {
      "title": "Peaky Blinders: The Immortal Man",
      "type": "movie",
      "platform": "Netflix",
      "rank": 8,
      "description": "Un film o speciale legato alla celebre serie TV 'Peaky Blinders'.",
      "posterUrl": "https://image.tmdb.org/t/p/w500/4FXce93JqyDQl1B9lNv454Hs6qe.jpg"
    },
    {
      "title": "In viaggio con Joe",
      "type": "movie",
      "platform": "Netflix",
      "rank": 9,
      "description": "Una commedia americana di Tyler Perry, che segue Joe in un viaggio in auto con il nipote.",
      "posterUrl": "https://image.tmdb.org/t/p/w500/sp6HDicZNid6q4PrVRuKxUVMssv.jpg"
    },
    {
      "title": "Il mio anno a Oxford",
      "type": "movie",
      "platform": "Netflix",
      "rank": 10,
      "description": "Un dramma romantico che racconta la storia di Anna che studia a Oxford e incontra un misterioso giovane.",
      "posterUrl": "https://image.tmdb.org/t/p/w500/dEHMJlWsLfLtujXGANyeuxyuqd5.jpg"
    },
    {
      "title": "The Last of Us",
      "type": "tv",
      "platform": "Sky",
      "rank": 1,
      "description": "La serie post-apocalittica di successo tratta dall'omonimo videogioco, disponibile su NOW.",
      "posterUrl": "https://image.tmdb.org/t/p/w500/6WlffOd3bszyndGgsKGcUL6k28n.jpg"
    },
    {
      "title": "Euphoria",
      "type": "tv",
      "platform": "Sky",
      "rank": 2,
      "description": "La popolare serie drammatica adolescenziale, con la stagione 4 disponibile su NOW TV.",
      "posterUrl": "https://image.tmdb.org/t/p/w500/aJrG7OkoTMPWG5c8opz8a93AZPY.jpg"
    },
    {
      "title": "Gomorra - La Serie",
      "type": "tv",
      "platform": "Sky",
      "rank": 3,
      "description": "L'acclamata serie crime italiana, un classico tra le produzioni Sky Original.",
      "posterUrl": "https://image.tmdb.org/t/p/w500/wWxMYrClgTYlZt4hDPxy5eA9EKd.jpg"
    },
    {
      "title": "Hanno Ucciso l'Uomo Ragno - La leggendaria storia degli 883",
      "type": "tv",
      "platform": "Sky",
      "rank": 4,
      "description": "Una nuova serie Sky Original che racconta la storia della band italiana 883.",
      "posterUrl": "https://image.tmdb.org/t/p/w500/q7AkRxRGiD2s0lO8xY6RbVSPWFl.jpg"
    },
    {
      "title": "Un amore",
      "type": "tv",
      "platform": "Sky",
      "rank": 5,
      "description": "Una serie Sky Original che narra una storia d'amore che resiste al tempo e alla distanza.",
      "posterUrl": "https://image.tmdb.org/t/p/w500/814wqppJW0E4vmJMvhiYkEEdK2G.jpg"
    },
    {
      "title": "Masterchef Italia",
      "type": "tv",
      "platform": "Sky",
      "rank": 6,
      "description": "Il popolare cooking show italiano, un appuntamento fisso tra i programmi più commentati.",
      "posterUrl": "https://image.tmdb.org/t/p/w500/wD8S0XLIrHsKzGuw5xPMjDCYYbq.jpg"
    },
    {
      "title": "Pechino Express",
      "type": "tv",
      "platform": "Sky",
      "rank": 7,
      "description": "Il reality show di avventura e viaggio, molto seguito dal pubblico.",
      "posterUrl": "https://image.tmdb.org/t/p/w500/97WBjxeRtwLwapHeHTig7Xt8xMd.jpg"
    },
    {
      "title": "Piedone: Uno sbirro a Napoli",
      "type": "movie",
      "platform": "Sky",
      "rank": 8,
      "description": "Un film italiano tra i più visti nella sezione cinema di Sky.",
      "posterUrl": ""
    },
    {
      "title": "Vermiglio",
      "type": "movie",
      "platform": "Sky",
      "rank": 9,
      "description": "Un film drammatico italiano presente tra i titoli più popolari.",
      "posterUrl": "https://image.tmdb.org/t/p/w500/6buo5I8pAEIXIa8r9oPna9viNZ3.jpg"
    },
    {
      "title": "Outlander",
      "type": "tv",
      "platform": "Sky",
      "rank": 10,
      "description": "La serie drammatica storico-fantastica, con la stagione 8 disponibile su NOW TV.",
      "posterUrl": "https://image.tmdb.org/t/p/w500/bxBmfyzK0ARF9hqf2pbFWsddH14.jpg"
    }
  ]
}